realtime_websocket_conversation/__init__.py
realtime_websocket_conversation/ws.py
realtime_websocket_conversation-0.1.2.dist-info/METADATA
realtime_websocket_conversation-0.1.2.dist-info/WHEEL
realtime_websocket_conversation-0.1.2.dist-info/RECORD
