Metadata-Version: 2.4
Name: realtime-websocket-conversation
Version: 0.1.2
Summary: Python library that provides a websocket endpoint handler for FastAPI to stream between Twilio and OpenAI realtime.
Project-URL: Homepage, https://github.com/anth-dinosaur/realtime-websocket-conversation
Project-URL: Issues, https://github.com/anth-dinosaur/realtime-websocket-conversation/issues
Requires-Python: >=3.9
Requires-Dist: fastapi>=0.115.11
Requires-Dist: openai-agents>=0.0.4
Requires-Dist: openai>=1.66.3
Requires-Dist: twilio>=9.5.0
Requires-Dist: websockets>=15.0.1
